Complete_Modules_Pipeline/Codes/Individual_Instructions_And_SeqenceOf_Instructions/ALU.v
/*
* NAME-1: Yenumula Venkat Kumar 
* Rollno: 191CS263 
* Date of Writing: 13-03-2021
FROM THE PREVIOUS ASSIGNMENT A2
*/

module mux2_1 (out, i0, i1, s0); 
    input i0, i1; 
    input s0;
    output out;
    reg out;
    always @( s0 or i0 or i1 )
        case ({ s0}) 
        1'b0 : out = i0;
        1'b1 : out = i1;
        // default: $display("Invalid control signals"); 
    endcase
endmodule

module mux4_1 (result, i0, i1, i2, i3, s); 
    input i0, i1, i2, i3; 
    input [1:0] s;
    output result;
    reg result;
    always @( s[0] or s[1] or i0 or i1 or i2 or i3 )
        case ({s[1],s[0]}) 
            2'b00 : result = i0;
            2'b01 : result = i1;
            2'b10 : result = i2;
            2'b11 : result = i3;
        // default: $display("Invalid control signals"); 
    endcase
endmodule

/* FULL ADDER AND SUBTRACTOR*/
module FAS(sum,carry_out,a,b,carry_in);
    input  a,b,carry_in;
    output sum, carry_out;

    assign sum = (~a & ~b & carry_in) | (~a & b & ~carry_in) | (a & ~b & ~carry_in) | (a & b & carry_in); 
    assign carry_out = (a & b) | (b & carry_in) | (carry_in & a); 
    
endmodule

module AND(and_out,input1,input2);
    input input1;
    input input2;
    output and_out;
    assign and_out = input1 & input2;
endmodule

module OR(or_out,input1,input2);
    input input1;
    input input2;
    output or_out;
    assign or_out = input1 | input2;
endmodule

module xor_behavioural(y,a,b);
    // I/o port declarations
    input a,b;
    output y;
	 
    // no net

    // behavioural 
	assign y = (~a & b) | (a & ~b);
    
endmodule

module ALU (alu_out,alu_carry_out,A,B,alu_carry_in,Operation);
    input A;
    input B;
    input alu_carry_in;
    input [3:0] Operation;
    output reg  alu_out;
    output wire  alu_carry_out;

    wire i0_1,i1_1;
    wire out1;
    assign i0_1 = A;
    assign i1_1 = ~A;
    mux2_1 m1(out1,i0_1,i1_1,Operation[3]);

    //MUX 2
    wire i0_2,i1_2;
    wire out2;
    assign i0_2 = B;
    assign i1_2 = ~B;
    mux2_1 m2(out2,i0_2,i1_2,Operation[2]);

    // AND
    wire and1,carry_outt,summ,sum_,carry_out_;
    //FAS addsub2(summ,carry_outt,out1,out2,alu_carry_in);
    //assign alu_carry_out = carry_outt;
    AND and_1(and1,out1,out2);

    wire or1;
    //FAS addsub3(sum_,carry_out_,out1,out2,alu_carry_in);
    //assign alu_carry_out = carry_out_;
    OR or_1(or1,out1,out2);

    // adder or subtractor
    wire sum, carry_out;
    FAS addsub1(sum,carry_out,out1,out2,alu_carry_in);
    assign alu_carry_out = carry_out;

    always @(*)
    begin
        case ({Operation[3], Operation[2],Operation[1],Operation[0]}) 
            4'b0000: alu_out = and1; //AND A.B
            4'b0001: alu_out = or1;  //OR
            4'b0010: alu_out = sum;  //ADD
            4'b0110: alu_out = sum;  //SUB
            4'b1101: alu_out = or1;  //NAND
            4'b1100: alu_out = and1; //NOR
            4'b0111: alu_out = sum;  //SLT
            // default: $display("Invalid control signals"); 
        endcase
    end
endmodule //ALU

/* n-bit ripple carry ALU */
module ALU_params(Alu_out,Alu_carry_out,A,B,Alu_carry_in,Operation);
    
    parameter N = 64;

    input [N-1:0] A,B;
    input Alu_carry_in;
    input [3:0] Operation;
    output [N-1:0] Alu_out;
    output Alu_carry_out;

    genvar i;

    wire [N:0] w;

    assign w[0] = Alu_carry_in;

    assign Alu_carry_out = w[N];
    // assign Setlt = set[0];
    generate for( i = 0; i< N; i=i+1)
	 //begin:
    begin: alu
        ALU alu(.alu_out(Alu_out[i]),.alu_carry_out(w[i+1]),.A(A[i]),.B(B[i]),.alu_carry_in(w[i]),.Operation(Operation));
    end
	 endgenerate
 
endmodule

module Zero_check(out,in);
    parameter N = 64; 
    input [N-1:0] in;
    output out; 
    assign out = in ? 0:1;
endmodule //ALU_tb

module SLT(out0,in0,coutt,overfg);
    input in0;
    input overfg;
    input coutt;
    wire w_1;
    output wire out0; 
    xor_behavioural xor_gate(w_1,in0,overfg);
    xor_behavioural xor_gate2(out0,w_1,coutt);
endmodule //ALU_tb

module Overflow(flag,a,b,bin,cin,cout,sumout);
    input a,b,bin,cout,cin,sumout;
    output flag;
    assign flag = (cin!=cout)?1:0;

endmodule //ALU_tb

ALU/codes/04_ALU_CU.v
/*
* Date of Writing: 13-03-2021  
*/

/*MODULE FOR ALU CU STRUCTURAL IMPLEMENTATION*/
module ALU_CU(operation,fun6,AluOp);
   
    // I/O port declarations
    input [5:0] fun6;
    input [1:0] AluOp;
    output [3:0] operation;

    // assign operation[3] = 0;
    // 2 wires
    wire w1,w2;
    OR or2(w1,fun6[3],fun6[0]);

    AND and2(operation[0],w1,AluOp[1]);
    OR or4(operation[1],~fun6[2],~AluOp[1]);

    AND and4(w2,fun6[1],AluOp[1]);
    OR or3(operation[2],w2,AluOp[0]);

    AND and5(operation[3],AluOp[0],~AluOp[0]);

endmodule //ALU_CU

Complete_Modules_Pipeline/Codes/Individual_Instructions_And_SeqenceOf_Instructions/ALU_CU_tb.v
/*
* NAME-1: Yenumula Venkat Kumar 
* Rollno: 191CS263 
* Date of Writing: 13-03-2021  
*/

module ALU_CU_tb();
   /* reg to feed to Fun6,ALUOp*/

    reg [5:0] Fun6;
    reg [1:0] ALUOp;
    wire [3:0] Operation;
   
    /*Instantiate the DUT*/
    ALU_CU alucuu(Operation,Fun6,ALUOp);
    /*stimulus
    * create and feed input combinations
    * to the DUT */


    /*Procedural statement */
    initial
    begin
    /*print input/output signals to/from the DUT */ 
        $dumpfile("ALU_CU.vcd");
        $dumpvars(0,ALU_CU_tb);
        $monitor($time,". Operation: %b, Fun6: %b , ALUOp: %b",Operation,Fun6,ALUOp);
        begin
            /*GIVEN INPUTS BASED ON THE PPTS OF CU*/
            #5 Fun6 = 6'b000000; ALUOp = 2'b00;
            #5 Fun6 = 6'b000000; ALUOp = 2'b01;
            #5 Fun6 = 6'b000000; ALUOp = 2'b10;
            #5 Fun6 = 6'b000010; ALUOp = 2'b10;
            #5 Fun6 = 6'b000100; ALUOp = 2'b10;
            #5 Fun6 = 6'b000101; ALUOp = 2'b10;
            #5 Fun6 = 6'b000010; ALUOp = 2'b10;
        end
        #10 $finish;
    end
endmodule //ALU_CU_tb

Complete_Modules_Pipeline/Codes/Individual_Instructions_And_SeqenceOf_Instructions/ALU_CU.vcd
$date
	Fri Apr 02 11:41:35 2021
$end
$version
	Icarus Verilog
$end
$timescale
	1s
$end
$scope module ALU_CU_tb $end
$var wire 4 ! Operation [3:0] $end
$var reg 2 " ALUOp [1:0] $end
$var reg 6 # Fun6 [5:0] $end
$scope module alucuu $end
$var wire 2 $ AluOp [1:0] $end
$var wire 6 % fun6 [5:0] $end
$var wire 1 & w2 $end
$var wire 1 ' w1 $end
$var wire 4 ( operation [3:0] $end
$scope module and2 $end
$var wire 1 ) and_out $end
$var wire 1 * input2 $end
$var wire 1 ' input1 $end
$upscope $end
$scope module and4 $end
$var wire 1 & and_out $end
$var wire 1 + input1 $end
$var wire 1 , input2 $end
$upscope $end
$scope module and5 $end
$var wire 1 - and_out $end
$var wire 1 . input1 $end
$var wire 1 / input2 $end
$upscope $end
$scope module or2 $end
$var wire 1 0 input1 $end
$var wire 1 1 input2 $end
$var wire 1 ' or_out $end
$upscope $end
$scope module or3 $end
$var wire 1 & input1 $end
$var wire 1 2 input2 $end
$var wire 1 3 or_out $end
$upscope $end
$scope module or4 $end
$var wire 1 4 input1 $end
$var wire 1 5 input2 $end
$var wire 1 6 or_out $end
$upscope $end
$upscope $end
$upscope $end
$enddefinitions $end
#0
$dumpvars
x6
x5
x4
x3
x2
x1
x0
x/
x.
x-
x,
x+
x*
x)
bx (
x'
x&
bx %
bx $
bx #
bx "
bx !
$end
#5
16
0)
15
03
b10 !
b10 (
0-
1/
0'
14
0&
0*
0,
02
0.
00
01
0+
b0 "
b0 $
b0 #
b0 %
#10
b110 !
b110 (
13
0/
12
1.
b1 "
b1 $
#15
05
b10 !
b10 (
03
1/
1*
1,
02
0.
b10 "
b10 $
#20
b110 !
b110 (
13
1&
1+
b10 #
b10 %
#25
06
b0 !
b0 (
03
04
0&
0+
b100 #
b100 %
#30
b1 !
b1 (
1)
1'
11
b101 #
b101 %
#35
0)
16
b110 !
b110 (
13
0'
14
1&
01
1+
b10 #
b10 %
